{"sections":{"breadcrumb":{"type":"breadcrumb","settings":{}},"product-grid":{"type":"main-collection-product","blocks":{"c73b080b-e49b-49fc-ac0a-e950a5c235f2":{"type":"menu_collection","settings":{"menu_collection":"marcas","show_count":true}},"3ed92b5d-8259-48e9-91b4-7f47ec3d6028":{"type":"filter","settings":{}},"27730410-5f65-46ed-b076-8895a5043877":{"type":"products","settings":{"title":"Featured","collection":"featured","limit":"3"}}},"block_order":["c73b080b-e49b-49fc-ac0a-e950a5c235f2","3ed92b5d-8259-48e9-91b4-7f47ec3d6028","27730410-5f65-46ed-b076-8895a5043877"],"settings":{"sidebar_left":true,"sidebar_style":"1","sidebar_right":false,"collection_products_count":"9","collection_view_mode":"grid","product_layout":"outimage_aq_onimage","collection_columns":"3","space_product":"10","collection_alternative_image":true,"collection_aspect_ratio":"1","collection_ratio_width":"400","collection_ratio_height":"400","collection_product_category":true,"collection_rating_star":true,"collection_product_price":true,"collection_show_addtocart":true,"collection_grid_quickview":true,"collection_show_addtolinks":true,"collection_show_sale":true,"collection_show_discount":true,"collection_sale_label_text":"","collection_grid_swatch_type":"0","porto_settings_category_grid_one_column_mobile":true,"collection_infinite_scrolling":true,"collection_infinite_mode":"byscroll","collection_filters_enable":true,"collection_sorting_enable":true}}},"order":["breadcrumb","product-grid"]}